annotype/__init__.py
annotype-0.1.1.dist-info/DESCRIPTION.rst
annotype-0.1.1.dist-info/METADATA
annotype-0.1.1.dist-info/RECORD
annotype-0.1.1.dist-info/WHEEL
annotype-0.1.1.dist-info/metadata.json
annotype-0.1.1.dist-info/top_level.txt
