Metadata-Version: 2.0
Name: annotype
Version: 0.1.1
Summary: Marshmallow and Python 3 annotations
Home-page: https://github.com/cbourget/annotype
Author: Charles-Eric Bourget
Author-email: charlesericbourget@gmail.com
License: MIT
Download-URL: https://github.com/cbourget/annotype/archive/0.1.1.tar.gz
Keywords: annotation marshmallow type
Platform: UNKNOWN
Classifier: Development Status :: 3 - Alpha
Classifier: Intended Audience :: Developers
Classifier: Operating System :: POSIX :: Linux
Classifier: Programming Language :: Python :: 3.4
Classifier: Programming Language :: Python :: 3.5
Classifier: Programming Language :: Python :: 3.6
Requires-Dist: marshmallow (>=3.0.0b7)
Provides-Extra: tests
Requires-Dist: pytest; extra == 'tests'
Requires-Dist: coverage; extra == 'tests'
Requires-Dist: pytest-cov; extra == 'tests'
